imgproxy.py
imgproxy-1.0.0.dist-info/METADATA
imgproxy-1.0.0.dist-info/WHEEL
imgproxy-1.0.0.dist-info/top_level.txt
imgproxy-1.0.0.dist-info/RECORD
