Metadata-Version: 2.1
Name: imgproxy
Version: 1.0.0
Summary: Python support for ImgProxy
Home-page: https://github.com/klen/imgproxy
Author: Kirill Klenov
Author-email: horneds@gmail.com
License: MIT
Project-URL: Documentation, https://github.com/klen/imgproxy
Project-URL: Source code, https://github.com/klen/imgproxy
Project-URL: Issue tracker, https://github.com/klen/imgproxy
Keywords: imgproxy
Platform: UNKNOWN
Classifier: Development Status :: 5 - Production/Stable
Classifier: Intended Audience :: Developers
Classifier: License :: OSI Approved :: MIT License
Classifier: Programming Language :: Python
Classifier: Programming Language :: Python :: 3
Classifier: Programming Language :: Python :: 3.7
Classifier: Programming Language :: Python :: 3.8
Classifier: Programming Language :: Python :: 3.9
Classifier: Programming Language :: Python :: 3.10
Requires-Python: >=3.7
Requires-Dist: typing-extensions ; python_version < "3.8"
Provides-Extra: build
Requires-Dist: bump2version ; extra == 'build'
Requires-Dist: twine ; extra == 'build'
Requires-Dist: wheel ; extra == 'build'
Provides-Extra: tests
Requires-Dist: pytest ; extra == 'tests'
Requires-Dist: pytest-mypy ; extra == 'tests'
